LICENSE
README.md
setup.py
sw_python_utils.egg-info/PKG-INFO
sw_python_utils.egg-info/SOURCES.txt
sw_python_utils.egg-info/dependency_links.txt
sw_python_utils.egg-info/requires.txt
sw_python_utils.egg-info/top_level.txt
swutils/__init__.py
swutils/date.py
swutils/encrypt.py
swutils/network.py
swutils/phone.py
swutils/prod_calendar.py
swutils/requests.py
swutils/string.py
swutils/tests/__init__.py
swutils/tests/test_encrypt.py
swutils/tests/test_network.py