Metadata-Version: 1.0
Name: sw-python-utils
Version: 0.0.18
Summary: Soft Way company python utils.
Home-page: https://github.com/telminov/sw-python-utils
Author: Telminov Sergey
Author-email: UNKNOWN
License: The MIT License
Platform: UNKNOWN
